{
    "name": "Gemini CLI & TypeScript Dev",
    "image": "mcr.microsoft.com/devcontainers/typescript-node:1-20-bookworm",
    "features": {
        "ghcr.io/devcontainers/features/git:1": {},
        "ghcr.io/devcontainers/features/github-cli:1": {},
        "ghcr.io/devcontainers/features/docker-outside-of-docker:1": {}
    },
    // Docker起動時に .env ファイルを読み込ませる設定
    "runArgs": [
        "--env-file",
        ".env"
    ],
    "customizations": {
        "vscode": {
            // コンテナ起動時に自動で入れたいVS Code拡張機能
            "extensions": [
                "dbaeumer.vscode-eslint",
                "esbenp.prettier-vscode",
                "ms-vscode.vscode-typescript-next"
            ],
            "settings": {
                "terminal.integrated.defaultProfile.linux": "bash"
            }
        }
    },
    // コンテナユーザーをnode(非root)に設定
    "remoteUser": "node",
    // コンテナ作成後に実行されるコマンド
    // ここでGemini CLIをグローバルインストールします
    "postCreateCommand": "bash .devcontainer/setup.sh"
}